libica/__init__.py
libica/openapi/__init__.py
libica/openapi/v2/__init__.py
libica/openapi/v2/api_client.py
libica/openapi/v2/configuration.py
libica/openapi/v2/exceptions.py
libica/openapi/v2/model_utils.py
libica/openapi/v2/rest.py
libica/openapi/v2/api/__init__.py
libica/openapi/v2/api/analysis_storage_api.py
libica/openapi/v2/api/bundle_api.py
libica/openapi/v2/api/bundle_data_api.py
libica/openapi/v2/api/bundle_data_linking_batch_api.py
libica/openapi/v2/api/bundle_data_unlinking_batch_api.py
libica/openapi/v2/api/bundle_pipeline_api.py
libica/openapi/v2/api/bundle_sample_api.py
libica/openapi/v2/api/bundle_tool_api.py
libica/openapi/v2/api/connector_api.py
libica/openapi/v2/api/data_api.py
libica/openapi/v2/api/data_format_api.py
libica/openapi/v2/api/docker_image_api.py
libica/openapi/v2/api/entitled_bundle_api.py
libica/openapi/v2/api/entitlement_detail_api.py
libica/openapi/v2/api/event_code_api.py
libica/openapi/v2/api/event_log_api.py
libica/openapi/v2/api/git_credentials_api.py
libica/openapi/v2/api/job_api.py
libica/openapi/v2/api/metadata_model_api.py
libica/openapi/v2/api/notification_channel_api.py
libica/openapi/v2/api/pipeline_api.py
libica/openapi/v2/api/pipeline_language_api.py
libica/openapi/v2/api/project_analysis_api.py
libica/openapi/v2/api/project_analysis_creation_batch_api.py
libica/openapi/v2/api/project_analysis_storage_api.py
libica/openapi/v2/api/project_api.py
libica/openapi/v2/api/project_base_api.py
libica/openapi/v2/api/project_base_job_api.py
libica/openapi/v2/api/project_base_table_api.py
libica/openapi/v2/api/project_custom_events_api.py
libica/openapi/v2/api/project_custom_notification_subscriptions_api.py
libica/openapi/v2/api/project_data_api.py
libica/openapi/v2/api/project_data_copy_batch_api.py
libica/openapi/v2/api/project_data_linking_batch_api.py
libica/openapi/v2/api/project_data_move_batch_api.py
libica/openapi/v2/api/project_data_transfer_api.py
libica/openapi/v2/api/project_data_unlinking_batch_api.py
libica-3.2.dist-info/licenses/LICENSE
libica-3.2.dist-info/METADATA
libica-3.2.dist-info/WHEEL
libica-3.2.dist-info/top_level.txt
libica-3.2.dist-info/RECORD
