Metadata-Version: 2.4
Name: libica
Version: 3.2
Summary: Python SDK for Illumina Connected Analytics
Home-page: https://github.com/umccr/libica
Author: UMCCR and Contributors
Author-email: services@umccr.org
License: MIT
Project-URL: Bug Tracker, https://github.com/umccr/libica/issues
Classifier: Development Status :: 5 - Production/Stable
Classifier: Programming Language :: Python :: 3
Classifier: License :: OSI Approved :: MIT License
Classifier: Operating System :: OS Independent
Requires-Python: >=3.8
License-File: LICENSE
Requires-Dist: python-dateutil
Requires-Dist: urllib3
Requires-Dist: pydantic
Requires-Dist: typing-extensions
Provides-Extra: dev
Requires-Dist: pipdeptree; extra == "dev"
Requires-Dist: twine; extra == "dev"
Requires-Dist: setuptools; extra == "dev"
Requires-Dist: wheel; extra == "dev"
Requires-Dist: build; extra == "dev"
Requires-Dist: pdoc3; extra == "dev"
Requires-Dist: mkdocs; extra == "dev"
Requires-Dist: mkdocs-material; extra == "dev"
Requires-Dist: openapi-spec-validator; extra == "dev"
Requires-Dist: pre-commit; extra == "dev"
Requires-Dist: detect-secrets; extra == "dev"
Requires-Dist: black; extra == "dev"
Requires-Dist: ggshield; extra == "dev"
Provides-Extra: test
Requires-Dist: pytest; extra == "test"
Requires-Dist: pytest-cov; extra == "test"
Requires-Dist: flake8; extra == "test"
Requires-Dist: mockito; extra == "test"
Requires-Dist: tox; extra == "test"
Requires-Dist: nose2; extra == "test"
Dynamic: author
Dynamic: author-email
Dynamic: classifier
Dynamic: description
Dynamic: description-content-type
Dynamic: home-page
Dynamic: license
Dynamic: license-file
Dynamic: project-url
Dynamic: provides-extra
Dynamic: requires-dist
Dynamic: requires-python
Dynamic: summary
